setup.py
google/__init__.py
google/datastore/__init__.py
google/datastore/v1/__init__.py
google/datastore/v1/datastore_pb2.py
google/datastore/v1/entity_pb2.py
google/datastore/v1/query_pb2.py
proto_google_datastore_v1.egg-info/PKG-INFO
proto_google_datastore_v1.egg-info/SOURCES.txt
proto_google_datastore_v1.egg-info/dependency_links.txt
proto_google_datastore_v1.egg-info/namespace_packages.txt
proto_google_datastore_v1.egg-info/requires.txt
proto_google_datastore_v1.egg-info/top_level.txt