Metadata-Version: 1.1
Name: proto-google-datastore-v1
Version: 1.5.0
Summary: Generated files from protocol buffers for Cloud Datastore v1.
Home-page: https://github.com/GoogleCloudPlatform/google-cloud-datastore
Author: Google Inc
Author-email: gcd-discuss@google.com
License: Apache
Platform: UNKNOWN
Classifier: Development Status :: 5 - Production/Stable
Classifier: Intended Audience :: Developers
Classifier: Programming Language :: Python :: 2.7
